bookshelf/__init__.py
bookshelf/book.py
bookshelf/constants.py
bookshelf/dataset_structure.py
bookshelf/errors.py
bookshelf/py.typed
bookshelf/schema.py
bookshelf/shelf.py
bookshelf/utils.py
other_data.md
bookshelf-0.4.0.dist-info/METADATA
bookshelf-0.4.0.dist-info/WHEEL
bookshelf-0.4.0.dist-info/RECORD
